a4x/orchestration/__init__.py
a4x/orchestration/annotations.py
a4x/orchestration/command.py
a4x/orchestration/file.py
a4x/orchestration/plugin.py
a4x/orchestration/resources.py
a4x/orchestration/site.py
a4x/orchestration/task.py
a4x/orchestration/utils.py
a4x/orchestration/version.py
a4x/orchestration/workflow.py
a4x/orchestration/builtin_plugins/flux/__init__.py
a4x/orchestration/builtin_plugins/flux/flux_plugin.py
a4x/orchestration/builtin_plugins/flux/templates/batch_script.py.in
a4x/orchestration/builtin_plugins/flux/templates/batch_script.sh.in
a4x/orchestration/builtin_plugins/flux/templates/task_script.sh.in
a4x/orchestration/config/__init__.py
a4x/orchestration/config/reader.py
a4x/orchestration/config/validation.py
a4x/orchestration/config/writer.py
a4x_orchestration-0.1.0b3.dist-info/licenses/LICENSE
a4x_orchestration-0.1.0b3.dist-info/licenses/NOTICE
a4x_orchestration-0.1.0b3.dist-info/METADATA
a4x_orchestration-0.1.0b3.dist-info/WHEEL
a4x_orchestration-0.1.0b3.dist-info/top_level.txt
a4x_orchestration-0.1.0b3.dist-info/RECORD
