Metadata-Version: 2.4
Name: a4x-orchestration
Version: 0.1.0b3
Summary: Abstracts the process of configuring workflows for various workflow management systems (WMS)
Author-email: Ian Lumsden <ilumsden@vols.utk.edu>, Michela Taufer <mtaufer@utk.edu>
Maintainer-email: Ian Lumsden <ilumsden@vols.utk.edu>, Michela Taufer <mtaufer@utk.edu>
License: 
Project-URL: Repository, https://github.com/Analytics4MD/a4x-orchestration
Classifier: Development Status :: 3 - Alpha
Classifier: Intended Audience :: Science/Research
Classifier: License :: OSI Approved :: Apache Software License
Classifier: Operating System :: POSIX :: Linux
Classifier: Programming Language :: Python :: 3.8
Classifier: Programming Language :: Python :: 3.9
Classifier: Programming Language :: Python :: 3.10
Classifier: Programming Language :: Python :: 3.11
Classifier: Programming Language :: Python :: 3.12
Classifier: Programming Language :: Python :: 3.13
Classifier: Programming Language :: Python :: 3.14
Classifier: Topic :: Scientific/Engineering
Requires-Python: >=3.8
License-File: LICENSE
License-File: NOTICE
Requires-Dist: importlib-metadata; python_version < "3.10"
Requires-Dist: StrEnum; python_version < "3.11"
Requires-Dist: ruamel.yaml==0.18.*
Requires-Dist: networkx
Requires-Dist: Jinja2
Requires-Dist: jsonschema~=4.23
Requires-Dist: referencing~=0.35
Dynamic: license-file
